Workbook

Sheet LEIA-ME
A1: Axtro Human Sales AI — Unit Economics
A3: Data das cotações de providers: | B3: 2026-07-13 (preços públicos; RECONFERIR antes de qualquer contrato — ver PENDENCIAS_EXTERNAS.md)
A4: Como usar: | B4: Edite apenas células AMARELAS (aba Premissas). Todo o resto é calculado por fórmula.
A5: Convenção de cores: | B5: Amarelo = input editável · Cinza = cálculo intermediário · Verde = resultado
A6: Moeda: | B6: Custos de providers em USD; preços de venda e margens em BRL (câmbio editável nas Premissas).
A7: Abas: | B7: Premissas → Custo_por_Minuto (5 cenários) → Planos_Margem (3 planos) → Breakeven
A8: Fonte dos preços: | B8: Tavus (pricing público), ElevenLabs, Cartesia, Deepgram, OpenAI, Anthropic, LiveKit, Telnyx, Recall.ai — detalhados em docs/operations/PROVIDER_STRATEGY.md
A9: Aviso: | B9: Modelo simplificado para decisão de pricing do MVP; não substitui contabilidade.

Sheet Premissas
A1: Premissas (edite apenas as células amarelas)
A3: Código | B3: Premissa | C3: Valor | D3: Unidade | E3: Nota / fonte (cotado 2026-07-13)
A4: FX | B4: Câmbio USD→BRL | C4: 5.3 | D4: BRL/USD | E4: Editável; PTAX aproximada na data
A5: STT | B5: Deepgram Nova streaming | C5: 0.0077 | D5: USD/min | E5: Pay-as-you-go, PT-BR
A6: LLM_RT | B6: LLM realtime (Haiku via gateway) | C6: 0.012 | D6: USD/min conversa | E6: Estimado: ~700 tokens in/out por turno, ~10 turnos/10min
A7: LLM_PC | B7: LLM pós-call (resumo/judge, Sonnet) | C7: 0.03 | D7: USD/sessão | E7: Custo por sessão, não por minuto
A8: TTS_EL | B8: ElevenLabs Flash v2.5 | C8: 0.06 | D8: USD/min falado | E8: Equivalente por minuto de áudio gerado
A9: TTS_CA | B9: Cartesia Sonic (fallback) | C9: 0.025 | D9: USD/min falado | E9: —
A10: S2S | B10: OpenAI Realtime (voz S2S) | C10: 0.1 | D10: USD/min | E10: Ordem de grandeza; varia com áudio in/out
A11: AVATAR | B11: Tavus CVI (overage) | C11: 0.34 | D11: USD/min vídeo | E11: Faixa 0,32–0,37; Growth US$397/1.250min
A12: LK | B12: LiveKit Cloud | C12: 0.0075 | D12: USD/participante-min | E12: 2 participantes ⇒ 2x por minuto de call
A13: TEL | B13: Telnyx voz US | C13: 0.007 | D13: USD/min | E13: BR sob consulta na F3
A14: RECALL | B14: Recall.ai bot | C14: 0.8 | D14: USD/hora | E14: Verificar na contratação (F3)
A15: SPK | B15: % do tempo em que a IA fala | C15: 0.4 | D15: fração | E15: Método Silva: lead fala ~60%
... A20: FIXO | B20: Custos fixos mensais (infra base+ferramentas) | C20: 900 | D20: USD/mês | E20: Doppler, Grafana, Sentry, Vercel, Fly base, Supabase Pro etc.

Sheet Custo_por_Minuto
A1: Custo por minuto de conversa — 5 cenários
A2: Fórmulas referenciam Premissas. TTS/Avatar multiplicados pela fração de fala da IA (SPK).
A4: Componente | B4: S1 Voz econômica (pipeline+Cartesia) | C4: S2 Voz premium (pipeline+ElevenLabs) | D4: S3 Voz S2S (OpenAI Realtime) | E4: S4 Vídeo avatar (S2 + Tavus) | F4: S5 Telefonia (S2 + Telnyx, sem LiveKit 2º part.)
A5: STT | B5: =Premissas!$C$5 -> 0.0077 | C5: =Premissas!$C$5 -> 0.0077 | D5: =0 -> 0 | E5: =Premissas!$C$5 -> 0.0077 | F5: =Premissas!$C$5 -> 0.0077
A6: LLM realtime | B6: =Premissas!$C$6 -> 0.012 | C6: =Premissas!$C$6 -> 0.012 | D6: =0 -> 0 | E6: =Premissas!$C$6 -> 0.012 | F6: =Premissas!$C$6 -> 0.012
A7: S2S (tudo-em-um) | B7: =0 -> 0 | C7: =0 -> 0 | D7: =Premissas!$C$10 -> 0.1 | E7: =0 -> 0 | F7: =0 -> 0
A8: TTS × fração fala IA | B8: =Premissas!$C$9*Premissas!$C$15 -> 0.01 | C8: =Premissas!$C$8*Premissas!$C$15 -> 0.024 | D8: =0 -> 0 | E8: =Premissas!$C$8*Premissas!$C$15 -> 0.024 | F8: =Premissas!$C$8*Premissas!$C$15 -> 0.024
A9: Avatar × fração fala? (stream contínuo ⇒ 100%) | B9: =0 -> 0 | C9: =0 -> 0 | D9: =0 -> 0 | E9: =Premissas!$C$11 -> 0.34 | F9: =0 -> 0
A10: LiveKit (2 participantes) | B10: =2*Premissas!$C$12 -> 0.015 | C10: =2*Premissas!$C$12 -> 0.015 | D10: =2*Premissas!$C$12 -> 0.015 | E10: =2*Premissas!$C$12 -> 0.015 | F10: =1*Premissas!$C$12 -> 0.0075
A11: Telefonia | B11: =0 -> 0 | C11: =0 -> 0 | D11: =0 -> 0 | E11: =0 -> 0 | F11: =Premissas!$C$13 -> 0.007
A12: Infra rateada | B12: =Premissas!$C$18 -> 0.005 | C12: =Premissas!$C$18 -> 0.005 | D12: =Premissas!$C$18 -> 0.005 | E12: =Premissas!$C$18 -> 0.005 | F12: =Premissas!$C$18 -> 0.005
A13: TOTAL USD/min | B13: =SUM(B5:B12) -> 0.0497 | C13: =SUM(C5:C12) -> 0.0637 | D13: =SUM(D5:D12) -> 0.12 | E13: =SUM(E5:E12) -> 0.4037 | F13: =SUM(F5:F12) -> 0.0632
A14: TOTAL BRL/min | B14: =B13*Premissas!$C$4 -> 0.26341 | C14: =C13*Premissas!$C$4 -> 0.33761 | D14: =D13*Premissas!$C$4 -> 0.636 | E14: =E13*Premissas!$C$4 -> 2.13961 | F14: =F13*Premissas!$C$4 -> 0.33496
A16: Custo por call de qualificação (DUR_Q) | B16: =B14*Premissas!$C$16 -> 2.10728 | C16: =C14*Premissas!$C$16 -> 2.70088
A17: Custo por reunião de fechamento (DUR_C) | C17: =C14*Premissas!$C$17 -> 15.19245 | E17: =E14*Premissas!$C$17 -> 96.28245

Sheet Planos_Margem
A1: Planos e margem bruta (BRL/mês)
A2: Amarelo = defina preço e franquias. Mix: minutos de voz usam S2 (premium); vídeo usa S4; excedente cobrado à parte (linha 14+).
A4: Item | B4: Starter | C4: Pro | D4: Scale
A5: Preço mensal (BRL) | B5: 997 | C5: 2497 | D5: 5997
A6: Minutos de VOZ incluídos | B6: 500 | C6: 1500 | D6: 4000
A7: Minutos de VÍDEO incluídos | B7: 0 | C7: 200 | D7: 800
A8: Agentes ativos | B8: 1 | C8: 3 | D8: 10
A9: Custo voz (S2 × min voz) | B9: =B6*Custo_por_Minuto!$C$14 -> 168.805 | C9: =C6*Custo_por_Minuto!$C$14 -> 506.415 | D9: =D6*Custo_por_Minuto!$C$14 -> 1350.44
A10: Custo vídeo (S4 × min vídeo) | B10: =B7*Custo_por_Minuto!$E$14 -> 0 | C10: =C7*Custo_por_Minuto!$E$14 -> 427.922 | D10: =D7*Custo_por_Minuto!$E$14 -> 1711.688
A11: Custo pós-call (LLM_PC × calls estimadas) | B11: =(B6/Premissas!$C$16)*Premissas!$C$7*Premissas!$C$4 -> 9.9375 | C11: =(C6/Premissas!$C$16)*Premissas!$C$7*Premissas!$C$4 -> 29.8125 | D11: =(D6/Premissas!$C$16)*Premissas!$C$7*Premissas!$C$4 -> 79.5
A12: Custo total variável | B12: =SUM(B9:B11) -> 178.7425 | C12: =SUM(C9:C11) -> 964.1495 | D12: =SUM(D9:D11) -> 3141.628
A13: Margem bruta (R$) | B13: =B5-B12 -> 818.2575 | C13: =C5-C12 -> 1532.8505 | D13: =D5-D12 -> 2855.372
A14: Margem bruta (%) | B14: =(B5-B12)/B5 -> 0.82071966 | C14: =(C5-C12)/C5 -> 0.61387685 | D14: =(D5-D12)/D5 -> 0.4761334
A15: Margem ≥ alvo? | B15: =IF(B14>=Premissas!$C$19,"OK","ABAIXO") -> OK | C15: =IF(C14>=Premissas!$C$19,"OK","ABAIXO") -> ABAIXO | D15: =IF(D14>=Premissas!$C$19,"OK","ABAIXO") -> ABAIXO
A17: Excedente sugerido — voz (BRL/min, custo S2 ÷ (1−alvo)) | B17: =Custo_por_Minuto!$C$14/(1-Premissas!$C$19) -> 1.1253667
A18: Excedente sugerido — vídeo (BRL/min, custo S4 ÷ (1−alvo)) | B18: =Custo_por_Minuto!$E$14/(1-Premissas!$C$19) -> 7.1320333

Sheet Breakeven
A1: Breakeven mensal
A3: Custos fixos (USD/mês, Premissas!FIXO) | B3: =Premissas!$C$20 -> 900
A4: Custos fixos (BRL/mês) | B4: =B3*Premissas!$C$4 -> 4770
A6: Métrica | B6: Starter | C6: Pro | D6: Scale
A7: Margem bruta por cliente (R$) | B7: =Planos_Margem!B13 -> 818.2575 | C7: =Planos_Margem!C13 -> 1532.8505 | D7: =Planos_Margem!D13 -> 2855.372
A8: Clientes p/ breakeven (fixos ÷ margem) | B8: =IF(B7>0,ROUNDUP($B$4/B7,0),"n/a") -> 6 | C8: =IF(C7>0,ROUNDUP($B$4/C7,0),"n/a") -> 4 | D8: =IF(D7>0,ROUNDUP($B$4/D7,0),"n/a") -> 2
A10: Leitura: com o mix 100% em um único plano; na prática o mix real fica entre Pro e Scale.
